mbc_unicode_input/__init__.py
mbc_unicode_input/main.py
mbc_unicode_input-0.2.0.dist-info/entry_points.txt
mbc_unicode_input-0.2.0.dist-info/WHEEL
mbc_unicode_input-0.2.0.dist-info/METADATA
mbc_unicode_input-0.2.0.dist-info/RECORD
