Metadata-Version: 2.1
Name: mbc-unicode-input
Version: 0.2.0
Summary: 
Author: Manuel Brea
Author-email: m.brea.carreras@gmail.com
Requires-Python: >=3.10,<4.0
Classifier: Programming Language :: Python :: 3
Classifier: Programming Language :: Python :: 3.10
Classifier: Programming Language :: Python :: 3.11
